[
  {
    "instance_id": "lane09_random",
    "signal_id": "sig_c353fa641e86",
    "slug": "btc-updown-15m-1784473200",
    "direction": "DOWN",
    "size_usd": 60.0,
    "entry_price": 0.65,
    "pnl_usd": -60.0,
    "won": false,
    "settled_at": "2026-07-19T15:16:16.936047Z",
    "entry_source": "enhanced_mispricing",
    "model_q_source": "advanced_ensemble_smoothed",
    "live_real_q": true,
    "enhanced_edge": 0.1855,
    "bandit_arm": "explore"
  },
  {
    "instance_id": "lane04_longshot",
    "signal_id": "sig_4b87f78e9413",
    "slug": "btc-updown-15m-1784475000",
    "direction": "DOWN",
    "size_usd": 60.0,
    "entry_price": 0.20000000000000004,
    "pnl_usd": -60.0,
    "won": false,
    "settled_at": "2026-07-19T15:47:18.798271Z",
    "entry_source": "enhanced_mispricing",
    "model_q_source": "barrier_cex_open",
    "live_real_q": true,
    "enhanced_edge": 0.23418,
    "bandit_arm": "explore"
  },
  {
    "instance_id": "lane10_depth",
    "signal_id": "sig_7078e241ca5f",
    "slug": "btc-updown-15m-1784475000",
    "direction": "DOWN",
    "size_usd": 60.0,
    "entry_price": 0.20000000000000004,
    "pnl_usd": -60.0,
    "won": false,
    "settled_at": "2026-07-19T15:47:19.170093Z",
    "entry_source": "enhanced_mispricing",
    "model_q_source": "barrier_cex_open",
    "live_real_q": true,
    "enhanced_edge": 0.22734,
    "bandit_arm": "explore"
  },
  {
    "instance_id": "lane06_garch",
    "signal_id": "sig_c0021c0d2573",
    "slug": "btc-updown-15m-1784475000",
    "direction": "DOWN",
    "size_usd": 60.0,
    "entry_price": 0.20000000000000004,
    "pnl_usd": -60.0,
    "won": false,
    "settled_at": "2026-07-19T15:47:19.352393Z",
    "entry_source": "enhanced_mispricing",
    "model_q_source": "barrier_cex_open",
    "live_real_q": true,
    "enhanced_edge": 0.29359,
    "bandit_arm": "explore"
  },
  {
    "instance_id": "lane08_legacy",
    "signal_id": "sig_44e46fd72b65",
    "slug": "btc-updown-15m-1784475000",
    "direction": "DOWN",
    "size_usd": 60.0,
    "entry_price": 0.1910551454624403,
    "pnl_usd": -60.0,
    "won": false,
    "settled_at": "2026-07-19T15:47:20.388553Z",
    "entry_source": "enhanced_mispricing",
    "model_q_source": "advanced_ensemble_smoothed",
    "live_real_q": true,
    "enhanced_edge": 0.20291,
    "bandit_arm": "explore"
  },
  {
    "instance_id": "lane01_baseline",
    "signal_id": "sig_e30cfe7204d4",
    "slug": "btc-updown-15m-1784475000",
    "direction": "DOWN",
    "size_usd": 60.0,
    "entry_price": 0.18187329493785998,
    "pnl_usd": -60.0,
    "won": false,
    "settled_at": "2026-07-19T15:47:21.461717Z",
    "entry_source": "enhanced_mispricing",
    "model_q_source": "barrier_cex_open",
    "live_real_q": true,
    "enhanced_edge": 0.19456,
    "bandit_arm": "explore"
  },
  {
    "instance_id": "lane09_random",
    "signal_id": "sig_c77ca367cb28",
    "slug": "btc-updown-15m-1784475000",
    "direction": "DOWN",
    "size_usd": 60.0,
    "entry_price": 0.18000000000000002,
    "pnl_usd": -60.0,
    "won": false,
    "settled_at": "2026-07-19T15:47:34.384932Z",
    "entry_source": "enhanced_mispricing",
    "model_q_source": "advanced_ensemble_smoothed",
    "live_real_q": true,
    "enhanced_edge": 0.2325,
    "bandit_arm": "explore"
  },
  {
    "instance_id": "lane08_legacy",
    "signal_id": "sig_922472c26302",
    "slug": "btc-updown-15m-1784475900",
    "direction": "UP",
    "size_usd": 60.0,
    "entry_price": 0.41100649292400127,
    "pnl_usd": 85.98,
    "won": true,
    "settled_at": "2026-07-19T16:03:10.737779Z",
    "entry_source": "enhanced_mispricing",
    "model_q_source": "advanced_ensemble_smoothed",
    "live_real_q": true,
    "enhanced_edge": 0.23136,
    "bandit_arm": "explore"
  },
  {
    "instance_id": "lane01_baseline",
    "signal_id": "sig_957ccd89aa8b",
    "slug": "btc-updown-15m-1784475900",
    "direction": "UP",
    "size_usd": 60.0,
    "entry_price": 0.40117416829745595,
    "pnl_usd": -60.0,
    "won": false,
    "settled_at": "2026-07-19T16:03:12.400345Z",
    "entry_source": "enhanced_mispricing",
    "model_q_source": "barrier_cex_open",
    "live_real_q": true,
    "enhanced_edge": 0.3046,
    "bandit_arm": "explore"
  },
  {
    "instance_id": "lane04_longshot",
    "signal_id": "sig_7cb7664427b3",
    "slug": "btc-updown-15m-1784475900",
    "direction": "UP",
    "size_usd": 60.0,
    "entry_price": 0.39046627387240956,
    "pnl_usd": 93.66,
    "won": true,
    "settled_at": "2026-07-19T16:03:12.852930Z",
    "entry_source": "enhanced_mispricing",
    "model_q_source": "barrier_cex_open",
    "live_real_q": true,
    "enhanced_edge": 0.30434,
    "bandit_arm": "explore"
  },
  {
    "instance_id": "lane06_garch",
    "signal_id": "sig_17d330e692e9",
    "slug": "btc-updown-15m-1784475900",
    "direction": "UP",
    "size_usd": 60.0,
    "entry_price": 0.40837757423720905,
    "pnl_usd": 86.92,
    "won": true,
    "settled_at": "2026-07-19T16:03:13.017162Z",
    "entry_source": "enhanced_mispricing",
    "model_q_source": "barrier_cex_open",
    "live_real_q": true,
    "enhanced_edge": 0.31885,
    "bandit_arm": "explore"
  },
  {
    "instance_id": "lane10_depth",
    "signal_id": "sig_b44fd74f0c37",
    "slug": "btc-updown-15m-1784475900",
    "direction": "UP",
    "size_usd": 60.0,
    "entry_price": 0.4093726850949355,
    "pnl_usd": 86.57,
    "won": true,
    "settled_at": "2026-07-19T16:03:13.083960Z",
    "entry_source": "enhanced_mispricing",
    "model_q_source": "barrier_cex_open",
    "live_real_q": true,
    "enhanced_edge": 0.30557,
    "bandit_arm": "explore"
  },
  {
    "instance_id": "lane02_chainlink",
    "signal_id": "sig_a60f24caabcc",
    "slug": "btc-updown-15m-1784475900",
    "direction": "UP",
    "size_usd": 60.0,
    "entry_price": 0.28,
    "pnl_usd": -60.0,
    "won": false,
    "settled_at": "2026-07-19T16:03:15.070783Z",
    "entry_source": "enhanced_mispricing",
    "model_q_source": "barrier_cex_open",
    "live_real_q": true,
    "enhanced_edge": 0.30382,
    "bandit_arm": "explore"
  },
  {
    "instance_id": "lane09_random",
    "signal_id": "sig_04c2e2e7cb8a",
    "slug": "btc-updown-15m-1784475900",
    "direction": "DOWN",
    "size_usd": 60.0,
    "entry_price": 0.6458220531922528,
    "pnl_usd": 32.9,
    "won": true,
    "settled_at": "2026-07-19T16:03:21.477624Z",
    "entry_source": "enhanced_mispricing",
    "model_q_source": "advanced_ensemble_smoothed",
    "live_real_q": true,
    "enhanced_edge": 0.1855,
    "bandit_arm": "explore"
  },
  {
    "instance_id": "lane09_random",
    "signal_id": "sig_31c015fa300e",
    "slug": "btc-updown-15m-1784476800",
    "direction": "DOWN",
    "size_usd": 60.0,
    "entry_price": 0.81,
    "pnl_usd": 14.07,
    "won": true,
    "settled_at": "2026-07-19T16:19:06.525470Z",
    "entry_source": "enhanced_mispricing",
    "model_q_source": "advanced_ensemble_smoothed",
    "live_real_q": true,
    "enhanced_edge": 0.12,
    "bandit_arm": "explore"
  },
  {
    "instance_id": "lane09_random",
    "signal_id": "sig_a1d83e73dedb",
    "slug": "btc-updown-15m-1784477700",
    "direction": "UP",
    "size_usd": 60.0,
    "entry_price": 0.64,
    "pnl_usd": 33.75,
    "won": true,
    "settled_at": "2026-07-19T16:34:49.180675Z",
    "entry_source": "enhanced_mispricing",
    "model_q_source": "advanced_ensemble_smoothed",
    "live_real_q": true,
    "enhanced_edge": 0.1845,
    "bandit_arm": "explore"
  },
  {
    "instance_id": "lane08_legacy",
    "signal_id": "sig_416a743b9a00",
    "slug": "btc-updown-15m-1784480400",
    "direction": "DOWN",
    "size_usd": 60.0,
    "entry_price": 0.1665833749791771,
    "pnl_usd": -60.0,
    "won": false,
    "settled_at": "2026-07-19T17:16:03.259207Z",
    "entry_source": "enhanced_mispricing",
    "model_q_source": "advanced_ensemble_smoothed",
    "live_real_q": true,
    "enhanced_edge": 0.24231,
    "bandit_arm": "exploit"
  },
  {
    "instance_id": "lane01_baseline",
    "signal_id": "sig_3570b786e6c9",
    "slug": "btc-updown-15m-1784480400",
    "direction": "DOWN",
    "size_usd": 60.0,
    "entry_price": 0.12389569359218355,
    "pnl_usd": -60.0,
    "won": false,
    "settled_at": "2026-07-19T17:16:05.733480Z",
    "entry_source": "enhanced_mispricing",
    "model_q_source": "barrier_cex_open",
    "live_real_q": true,
    "enhanced_edge": 0.16206,
    "bandit_arm": "exploit"
  },
  {
    "instance_id": "lane01_baseline",
    "signal_id": "sig_31da8e660702",
    "slug": "btc-updown-15m-1784481300",
    "direction": "UP",
    "size_usd": 60.0,
    "entry_price": 0.29960278469512996,
    "pnl_usd": -60.0,
    "won": false,
    "settled_at": "2026-07-19T17:31:50.187194Z",
    "entry_source": "enhanced_mispricing",
    "model_q_source": "barrier_cex_open",
    "live_real_q": true,
    "enhanced_edge": 0.19982,
    "bandit_arm": "explore"
  },
  {
    "instance_id": "lane04_longshot",
    "signal_id": "sig_bfe5d7c70e50",
    "slug": "btc-updown-15m-1784481300",
    "direction": "UP",
    "size_usd": 60.0,
    "entry_price": 0.30250592000832704,
    "pnl_usd": -60.0,
    "won": false,
    "settled_at": "2026-07-19T17:31:57.654477Z",
    "entry_source": "enhanced_mispricing",
    "model_q_source": "barrier_cex_open",
    "live_real_q": true,
    "enhanced_edge": 0.20544,
    "bandit_arm": "exploit"
  },
  {
    "instance_id": "lane10_depth",
    "signal_id": "sig_366021445e24",
    "slug": "btc-updown-15m-1784481300",
    "direction": "UP",
    "size_usd": 60.0,
    "entry_price": 0.30250592000832704,
    "pnl_usd": -60.0,
    "won": false,
    "settled_at": "2026-07-19T17:31:58.658444Z",
    "entry_source": "enhanced_mispricing",
    "model_q_source": "barrier_cex_open",
    "live_real_q": true,
    "enhanced_edge": 0.21192,
    "bandit_arm": "explore"
  },
  {
    "instance_id": "lane06_garch",
    "signal_id": "sig_11296a27178b",
    "slug": "btc-updown-15m-1784481300",
    "direction": "UP",
    "size_usd": 60.0,
    "entry_price": 0.30250592000832704,
    "pnl_usd": -60.0,
    "won": false,
    "settled_at": "2026-07-19T17:31:58.875451Z",
    "entry_source": "enhanced_mispricing",
    "model_q_source": "barrier_cex_open",
    "live_real_q": true,
    "enhanced_edge": 0.23851,
    "bandit_arm": "exploit"
  },
  {
    "instance_id": "lane06_garch",
    "signal_id": "sig_45e1fc08399f",
    "slug": "btc-updown-15m-1784481300",
    "direction": "UP",
    "size_usd": 60.0,
    "entry_price": 0.30918460139436194,
    "pnl_usd": -60.0,
    "won": false,
    "settled_at": "2026-07-19T17:32:06.739478Z",
    "entry_source": "enhanced_mispricing",
    "model_q_source": "barrier_cex_open",
    "live_real_q": true,
    "enhanced_edge": 0.2897,
    "bandit_arm": "explore"
  },
  {
    "instance_id": "lane02_chainlink",
    "signal_id": "sig_8c653f4f39d5",
    "slug": "btc-updown-15m-1784481300",
    "direction": "UP",
    "size_usd": 60.0,
    "entry_price": 0.27,
    "pnl_usd": -60.0,
    "won": false,
    "settled_at": "2026-07-19T17:32:09.284466Z",
    "entry_source": "enhanced_mispricing",
    "model_q_source": "barrier_cex_open",
    "live_real_q": true,
    "enhanced_edge": 0.17302,
    "bandit_arm": "exploit"
  },
  {
    "instance_id": "lane08_legacy",
    "signal_id": "sig_524756e0e75b",
    "slug": "btc-updown-15m-1784482200",
    "direction": "DOWN",
    "size_usd": 60.0,
    "entry_price": 0.24486477750770097,
    "pnl_usd": 185.03,
    "won": true,
    "settled_at": "2026-07-19T17:47:26.113433Z",
    "entry_source": "enhanced_mispricing",
    "model_q_source": "advanced_ensemble_smoothed",
    "live_real_q": true,
    "enhanced_edge": 0.19041,
    "bandit_arm": "explore"
  },
  {
    "instance_id": "lane04_longshot",
    "signal_id": "sig_eb7c648e45f7",
    "slug": "btc-updown-15m-1784482200",
    "direction": "DOWN",
    "size_usd": 60.0,
    "entry_price": 0.20902247157460274,
    "pnl_usd": 227.05,
    "won": true,
    "settled_at": "2026-07-19T17:47:44.890203Z",
    "entry_source": "enhanced_mispricing",
    "model_q_source": "barrier_cex_open",
    "live_real_q": true,
    "enhanced_edge": 0.09686,
    "bandit_arm": "exploit"
  },
  {
    "instance_id": "lane10_depth",
    "signal_id": "sig_f625f73867ba",
    "slug": "btc-updown-15m-1784482200",
    "direction": "DOWN",
    "size_usd": 60.0,
    "entry_price": 0.20902247157460274,
    "pnl_usd": 227.05,
    "won": true,
    "settled_at": "2026-07-19T17:47:46.341460Z",
    "entry_source": "enhanced_mispricing",
    "model_q_source": "barrier_cex_open",
    "live_real_q": true,
    "enhanced_edge": 0.09665,
    "bandit_arm": "explore"
  },
  {
    "instance_id": "lane06_garch",
    "signal_id": "sig_18b64af0c53d",
    "slug": "btc-updown-15m-1784482200",
    "direction": "DOWN",
    "size_usd": 60.0,
    "entry_price": 0.20798737549644603,
    "pnl_usd": 228.48,
    "won": true,
    "settled_at": "2026-07-19T17:47:53.645007Z",
    "entry_source": "enhanced_mispricing",
    "model_q_source": "barrier_cex_open",
    "live_real_q": true,
    "enhanced_edge": 0.27919,
    "bandit_arm": "explore"
  },
  {
    "instance_id": "lane02_chainlink",
    "signal_id": "sig_75d1f9a07c1f",
    "slug": "btc-updown-15m-1784482200",
    "direction": "DOWN",
    "size_usd": 60.0,
    "entry_price": 0.21999999999999995,
    "pnl_usd": 212.73,
    "won": true,
    "settled_at": "2026-07-19T17:47:56.561442Z",
    "entry_source": "enhanced_mispricing",
    "model_q_source": "barrier_cex_open",
    "live_real_q": true,
    "enhanced_edge": 0.11748,
    "bandit_arm": "exploit"
  },
  {
    "instance_id": "lane09_random",
    "signal_id": "sig_cc0658a26bb3",
    "slug": "btc-updown-15m-1784482200",
    "direction": "DOWN",
    "size_usd": 60.0,
    "entry_price": 0.24141132776230267,
    "pnl_usd": 188.54,
    "won": true,
    "settled_at": "2026-07-19T17:48:04.528423Z",
    "entry_source": "enhanced_mispricing",
    "model_q_source": "advanced_ensemble_smoothed",
    "live_real_q": true,
    "enhanced_edge": 0.2235,
    "bandit_arm": "explore"
  },
  {
    "instance_id": "lane09_random",
    "signal_id": "sig_e7c0ed5ff2cb",
    "slug": "btc-updown-15m-1784482200",
    "direction": "DOWN",
    "size_usd": 60.0,
    "entry_price": 0.21999999999999995,
    "pnl_usd": 212.73,
    "won": true,
    "settled_at": "2026-07-19T17:48:12.286458Z",
    "entry_source": "enhanced_mispricing",
    "model_q_source": "advanced_ensemble_smoothed",
    "live_real_q": true,
    "enhanced_edge": 0.2285,
    "bandit_arm": "exploit"
  }
]
